setup.cfg
setup.py
kibana/__init__.py
kibana/__main__.py
kibana/dotkibana.py
kibana/manager.py
kibana/mapping.py
kibana.egg-info/PKG-INFO
kibana.egg-info/SOURCES.txt
kibana.egg-info/dependency_links.txt
kibana.egg-info/entry_points.txt
kibana.egg-info/requires.txt
kibana.egg-info/top_level.txt