Metadata-Version: 1.1
Name: kibana
Version: 0.3
Summary: Kibana configuration index (.kibana) command line interface and python API (visualization import/export and mappings refresh)
Home-page: https://github.com/rfarley3/Kibana
Author: Ryan Farley
Author-email: rfarley@mitre.org
License: UNKNOWN
Download-URL: https://github.com/rfarley3/Kibana/tarball/0.3
Keywords: kibana,config,import,export,mappings
Platform: UNKNOWN
